pdf_helper/__init__.py
pdf_helper/__main__.py
pdf_helper/utils.py
pdf_helper-0.1.0.dist-info/WHEEL
pdf_helper-0.1.0.dist-info/entry_points.txt
pdf_helper-0.1.0.dist-info/METADATA
pdf_helper-0.1.0.dist-info/RECORD
