Metadata-Version: 2.3
Name: pdf-helper
Version: 0.1.0
Summary: A simple python script that helps with doing simple stuff with PDFs.
Author: CodeWriter21(Mehrad Pooryoussof)
Author-email: CodeWriter21(Mehrad Pooryoussof) <CodeWriter21@gmail.com>
License: MIT
Requires-Dist: log21>=3.0.0
Requires-Dist: pypdfium2>=4.30.0
Requires-Dist: pillow>=11.0.0
Requires-Python: >=3.9
